PyStructMatrix/__init__.py
pystructmatrix-1.0.4.dist-info/licenses/LICENSE
pystructmatrix-1.0.4.dist-info/licenses/LICENSEv2.txt
pystructmatrix-1.0.4.dist-info/METADATA
pystructmatrix-1.0.4.dist-info/WHEEL
pystructmatrix-1.0.4.dist-info/top_level.txt
pystructmatrix-1.0.4.dist-info/RECORD
