Metadata-Version: 2.4
Name: PyStructMatrix
Version: 1.0.4
Summary: Motor de análisis matricial para estructuras planas (2D)
Author-email: Anshel Chuquiviguel <anshel.chuquiviguel@utec.edu.pe>
License: MIT License
Requires-Python: >=3.6
License-File: LICENSE
License-File: LICENSEv2.txt
Requires-Dist: numpy
Requires-Dist: matplotlib
Dynamic: license-file
